atem/__init__.py
atem/atem_interpreter.py
atem/core.py
atem/model_train.py
atem/utils.py
atem-1.2.7.dist-info/LICENSE
atem-1.2.7.dist-info/METADATA
atem-1.2.7.dist-info/WHEEL
atem-1.2.7.dist-info/top_level.txt
atem-1.2.7.dist-info/RECORD
