Metadata-Version: 2.1
Name: atem
Version: 1.2.7
Summary: Adaptive task execution and machine learning package.
Home-page: https://github.com/CapitalRobotics/ATEM
Author: Torin Etheridge
Author-email: torinriley220@gmail.com
Classifier: Programming Language :: Python :: 3
Classifier: License :: OSI Approved :: MIT License
Classifier: Operating System :: OS Independent
Requires-Python: >=3.7
License-File: LICENSE
Requires-Dist: tensorflow>=2.0.0
Requires-Dist: numpy>=1.18.0
Requires-Dist: colorama>=0.4.6
